google_trans_new/__init__.py
google_trans_new/constant.py
google_trans_new/google_trans_new.py
google_trans_new_flickermi-1.1.9.6.dist-info/LICENSE
google_trans_new_flickermi-1.1.9.6.dist-info/METADATA
google_trans_new_flickermi-1.1.9.6.dist-info/WHEEL
google_trans_new_flickermi-1.1.9.6.dist-info/top_level.txt
google_trans_new_flickermi-1.1.9.6.dist-info/RECORD
