Metadata-Version: 2.1
Name: google-trans-new-flickermi
Version: 1.1.9.6
Summary: A free and unlimited python tools for google translate api.
Home-page: https://github.com/FlickerMi/google_trans_new
Author: Flicker
Author-email: libmi@foxmail.com
License: MIT Licence
License-File: LICENSE
